fsm/__init__.py
fsm/fsm.py
simple_fsm-0.0.2.dist-info/LICENSE
simple_fsm-0.0.2.dist-info/METADATA
simple_fsm-0.0.2.dist-info/WHEEL
simple_fsm-0.0.2.dist-info/top_level.txt
simple_fsm-0.0.2.dist-info/RECORD
