Metadata-Version: 2.1
Name: simple-fsm
Version: 0.0.2
Summary: Pythonic FSM
Home-page: https://github.com/freywaid/fsm
Author: Frey Waid"
Author-email: logophage1@gmail.com
License: UNKNOWN
Platform: UNKNOWN
Classifier: Programming Language :: Python :: 3
Classifier: License :: OSI Approved :: MIT License
Classifier: Operating System :: OS Independent
Requires-Python: >=3.6
